[
null,
{"id":1,"expanded":false,"name":"Start of Game","order":1,"parentId":0,"scrollX":832,"scrollY":800},
{"id":2,"expanded":true,"name":"WowWowWowWowWowWowWowWowWow","order":4,"parentId":0,"scrollX":533.6,"scrollY":329.6},
{"id":3,"expanded":false,"name":"Boss Fight","order":2,"parentId":0,"scrollX":685.1999999999999,"scrollY":487.2},
{"id":4,"expanded":false,"name":"Diamonds Golore!","order":3,"parentId":0,"scrollX":816,"scrollY":640},
{"id":5,"expanded":false,"name":"wow u won","order":5,"parentId":2,"scrollX":5749.333333333333,"scrollY":7866.666666666667}
]